jmon/__init__.py
jmon/machine.py
jmon-0.265.dist-info/DESCRIPTION.rst
jmon-0.265.dist-info/METADATA
jmon-0.265.dist-info/RECORD
jmon-0.265.dist-info/WHEEL
jmon-0.265.dist-info/metadata.json
jmon-0.265.dist-info/top_level.txt
